gemina/VERSION
gemina/__init__.py
gemina/__main__.py
pygemina-0.3.0.dist-info/LICENSE.txt
pygemina-0.3.0.dist-info/METADATA
pygemina-0.3.0.dist-info/WHEEL
pygemina-0.3.0.dist-info/entry_points.txt
pygemina-0.3.0.dist-info/top_level.txt
pygemina-0.3.0.dist-info/RECORD
